frd/__init__.py
frd/__main__.py
frd/frd_score.py
frd_score/__init__.py
frd_score/__main__.py
frd_score/frd.py
frd_score-0.0.2.dist-info/LICENSE
frd_score-0.0.2.dist-info/METADATA
frd_score-0.0.2.dist-info/WHEEL
frd_score-0.0.2.dist-info/entry_points.txt
frd_score-0.0.2.dist-info/top_level.txt
frd_score-0.0.2.dist-info/RECORD
