Metadata-Version: 2.1
Name: frd-score
Version: 0.0.2
Summary: Package for calculating Fréchet Radiomics Distance (FRD)
Home-page: https://github.com/RichardObi/frd-score
Download-URL: https://github.com/RichardObi/frd-score/archive/refs/tags/v.0.0.2.tar.gz
Author: Richard Osuala, Preeti Verma
License: Apache-2.0
Project-URL: Bug Tracker, https://github.com/RichardObi/frd-score/issues
Keywords: Radiomics,Frechet,Distance,medical,imaging,radiology,generative,synthetic,evaluation
Classifier: Programming Language :: Python :: 3
Classifier: License :: OSI Approved :: Apache Software License
Requires-Python: >=3.8
License-File: LICENSE
Requires-Dist: pyradiomics (==3.0.1a3)
Requires-Dist: numpy (>=1.23.5)
Requires-Dist: Pillow (>=10.3.0)
Requires-Dist: scipy (>=1.10.0)
Requires-Dist: opencv-contrib-python-headless (>=4.8.1.78)
Requires-Dist: SimpleITK (>=2.3.1)
Provides-Extra: dev
Requires-Dist: flake8 ; extra == 'dev'
Requires-Dist: flake8-bugbear ; extra == 'dev'
Requires-Dist: flake8-isort ; extra == 'dev'
Requires-Dist: black (==24.3.0) ; extra == 'dev'
Requires-Dist: isort ; extra == 'dev'
Requires-Dist: nox ; extra == 'dev'
Requires-Dist: pytest (>=8.1.1) ; extra == 'dev'
Requires-Dist: nibabel (>=3.2.1) ; extra == 'dev'
